
{
  "7emes": [
    {"numero": 1, "nom": "BAMBI", "post_nom": "BADIBANGA", "classe": "7èmes", "section": "EB section 1"},
    {"numero": 2, "nom": "BAUDOIN", "post_nom": "MUNGOBO", "classe": "7èmes", "section": "EB section 1"},
    {"numero": 3, "nom": "EBONDO", "post_nom": "DJIBU", "classe": "7èmes", "section": "EB section 1"},
    {"numero": 4, "nom": "EUNICE", "post_nom": "NYAMANDA", "classe": "7èmes", "section": "EB section 1"},
    {"numero": 5, "nom": "DJOHARI", "post_nom": "MUSA", "classe": "7èmes", "section": "EB section 1"},
    {"numero": 6, "nom": "ILUNGA", "post_nom": "KIKUDI", "classe": "7èmes", "section": "EB section 1"},
    {"numero": 7, "nom": "ILUNGA", "post_nom": "MWEPU", "classe": "7èmes", "section": "EB section 1"},
    {"numero": 8, "nom": "ILUNGA", "post_nom": "NTAMBWE", "classe": "7èmes", "section": "EB section 1"},
    {"numero": 9, "nom": "KABAMBA", "post_nom": "MWANAMUNA", "classe": "7èmes", "section": "EB section 1"},
    {"numero": 10, "nom": "KABILA", "post_nom": "MUSOKA", "classe": "7èmes", "section": "EB section 1"},
    {"numero": 11, "nom": "KABWIZA", "post_nom": "MILOLO", "classe": "7èmes", "section": "EB section 1"},
    {"numero": 12, "nom": "KAHULU", "post_nom": "wa NKULU", "classe": "7èmes", "section": "EB section 1"},
    {"numero": 13, "nom": "KALUME", "post_nom": "MUBA", "classe": "7èmes", "section": "EB section 1"},
    {"numero": 14, "nom": "KALWA", "post_nom": "KALUNGA", "classe": "7èmes", "section": "EB section 1"},
    {"numero": 15, "nom": "KALUNGA", "post_nom": "KALENDA", "classe": "7èmes", "section": "EB section 1"},
    {"numero": 16, "nom": "KALUMBU", "post_nom": "BESA", "classe": "7èmes", "section": "EB section 1"},
    {"numero": 17, "nom": "KALWA", "post_nom": "KYONJASALA", "classe": "7èmes", "section": "EB section 1"},
    {"numero": 18, "nom": "KAMANA", "post_nom": "KATONDE", "classe": "7èmes", "section": "EB section 1"},
    {"numero": 19, "nom": "KAMANDA", "post_nom": "wa KAMANDA", "classe": "7èmes", "section": "EB section 1"},
    {"numero": 20, "nom": "KANEWA", "post_nom": "MULASHI", "classe": "7èmes", "section": "EB section 1"},
    {"numero": 21, "nom": "KALAMBA", "post_nom": "NKOSHI", "classe": "7èmes", "section": "EB section 1"},
    {"numero": 22, "nom": "KASONGO", "post_nom": "NUMBI", "classe": "7èmes", "section": "EB section 1"},
    {"numero": 23, "nom": "KAT", "post_nom": "BADIBANGA", "classe": "7èmes", "section": "EB section 1"},
    {"numero": 24, "nom": "KATWISHI", "post_nom": "KIMPUTU", "classe": "7èmes", "section": "EB section 1"},
    {"numero": 25, "nom": "KAJIDI", "post_nom": "KWAMBA", "classe": "7èmes", "section": "EB section 1"},
    {"numero": 26, "nom": "KIHANGA", "post_nom": "SAFI", "classe": "7èmes", "section": "EB section 1"},
    {"numero": 1, "nom": "MUYAMBO", "post_nom": "wa KAJUMBA", "classe": "7èmes", "section": "EB section 2"},
    {"numero": 2, "nom": "MUYAMBO", "post_nom": "wa KAJUMBA", "classe": "7èmes", "section": "EB section 2"},
    {"numero": 3, "nom": "MUZADI", "post_nom": "NYEMBA", "classe": "7èmes", "section": "EB section 2"},
    {"numero": 4, "nom": "MWILA", "post_nom": "MULONGO", "classe": "7èmes", "section": "EB section 2"},
    {"numero": 5, "nom": "MWIKIZA", "post_nom": "ZINGIRE", "classe": "7èmes", "section": "EB section 2"},
    {"numero": 6, "nom": "NGALULA", "post_nom": "KALAMBA", "classe": "7èmes", "section": "EB section 2"},
    {"numero": 7, "nom": "NGOY", "post_nom": "PUTA", "classe": "7èmes", "section": "EB section 2"},
    {"numero": 8, "nom": "NTUMBA", "post_nom": "LONGO", "classe": "7èmes", "section": "EB section 2"},
    {"numero": 9, "nom": "NYEMBO", "post_nom": "MALISAWA", "classe": "7èmes", "section": "EB section 2"},
    {"numero": 10, "nom": "SAFI", "post_nom": "LOTSHUMBA", "classe": "7èmes", "section": "EB section 2"},
    {"numero": 11, "nom": "SASITA", "post_nom": "MBWIMBWE", "classe": "7èmes", "section": "EB section 2"},
    {"numero": 12, "nom": "SONGA", "post_nom": "NGANDWE", "classe": "7èmes", "section": "EB section 2"},
    {"numero": 13, "nom": "SENDEKI", "post_nom": "KADOTWE", "classe": "7èmes", "section": "EB section 2"},
    {"numero": 14, "nom": "TANGA", "post_nom": "NGANDU", "classe": "7èmes", "section": "EB section 2"},
    {"numero": 15, "nom": "TEMBO", "post_nom": "KASONGO", "classe": "7èmes", "section": "EB section 2"},
    {"numero": 16, "nom": "TAMBA-TAMBA", "post_nom": "KAZADI", "classe": "7èmes", "section": "EB section 2"},
    {"numero": 17, "nom": "MWAPE", "post_nom": "MUKUBE", "classe": "7èmes", "section": "EB section 2"},
    {"numero": 18, "nom": "TSHAMA", "post_nom": "KABOLE", "classe": "7èmes", "section": "EB section 2"},
    {"numero": 19, "nom": "TSHAMA", "post_nom": "KAJATA", "classe": "7èmes", "section": "EB section 2"},
    {"numero": 20, "nom": "TSHAMBA", "post_nom": "FAMBA", "classe": "7èmes", "section": "EB section 2"},
    {"numero": 21, "nom": "MWAMBI", "post_nom": "AMURI", "classe": "7èmes", "section": "EB section 2"},
    {"numero": 22, "nom": "NKULU", "post_nom": "wa NGOY", "classe": "7èmes", "section": "EB section 2"},
    {"numero": 23, "nom": "NGOY", "post_nom": "MWILAMBWE", "classe": "7èmes", "section": "EB section 2"},
    {"numero": 24, "nom": "KOSA", "post_nom": "KAINDA", "classe": "7èmes", "section": "EB section 2"},
    {"numero": 25, "nom": "KAZADI", "post_nom": "MWAMBA", "classe": "7èmes", "section": "EB section 2"},
    {"numero": 1, "nom": "KISIMBA", "post_nom": "KAPAMBWE", "classe": "7èmes", "section": "EB section 3"},
    {"numero": 2, "nom": "KITENGE", "post_nom": "wa KITENGE", "classe": "7èmes", "section": "EB section 3"},
    {"numero": 3, "nom": "KIUYA", "post_nom": "FAILA", "classe": "7èmes", "section": "EB section 3"},
    {"numero": 4, "nom": "KUMWIMBA", "post_nom": "KABONGO", "classe": "7èmes", "section": "EB section 3"},
    {"numero": 5, "nom": "KYALWE", "post_nom": "KITWA", "classe": "7èmes", "section": "EB section 3"},
    {"numero": 6, "nom": "LUKA", "post_nom": "KAFITA", "classe": "7èmes", "section": "EB section 3"},
    {"numero": 7, "nom": "LUNDA", "post_nom": "NGOMBE", "classe": "7èmes", "section": "EB section 3"},
    {"numero": 8, "nom": "LUVUNGU", "post_nom": "JUSTINE", "classe": "7èmes", "section": "EB section 3"},
    {"numero": 9, "nom": "LWAMBA", "post_nom": "KILALA", "classe": "7èmes", "section": "EB section 3"},
    {"numero": 10, "nom": "MAKILA", "post_nom": "UMBA", "classe": "7èmes", "section": "EB section 3"},
    {"numero": 11, "nom": "MBIYA", "post_nom": "GUSTAVE", "classe": "7èmes", "section": "EB section 3"},
    {"numero": 12, "nom": "MBUYI", "post_nom": "NTAMBWE", "classe": "7èmes", "section": "EB section 3"},
    {"numero": 13, "nom": "MBUYI", "post_nom": "NTAMBWE", "classe": "7èmes", "section": "EB section 3"},
    {"numero": 14, "nom": "MITEO", "post_nom": "NYURUKULA", "classe": "7èmes", "section": "EB section 3"},
    {"numero": 15, "nom": "MUBANGA", "post_nom": "KALONDE", "classe": "7èmes", "section": "EB section 3"},
    {"numero": 16, "nom": "MUDIMBI", "post_nom": "MWEMBO", "classe": "7èmes", "section": "EB section 3"},
    {"numero": 17, "nom": "MUFUNGA", "post_nom": "KABEKE", "classe": "7èmes", "section": "EB section 3"},
    {"numero": 18, "nom": "MUTING", "post_nom": "TSHIBAND", "classe": "7èmes", "section": "EB section 3"},
    {"numero": 19, "nom": "MUNAYE", "post_nom": "wa MUNAYE", "classe": "7èmes", "section": "EB section 3"},
    {"numero": 20, "nom": "MUKENDI", "post_nom": "KASONGO", "classe": "7èmes", "section": "EB section 3"},
    {"numero": 21, "nom": "MUKENDI", "post_nom": "MBIYA ISAAC", "classe": "7èmes", "section": "EB section 3"},
    {"numero": 22, "nom": "MUBELA", "post_nom": "MUSUMBA", "classe": "7èmes", "section": "EB section 3"},
    {"numero": 23, "nom": "MUKUBU", "post_nom": "KASONGO", "classe": "7èmes", "section": "EB section 3"},
    {"numero": 24, "nom": "MUKUNA", "post_nom": "MWAMBA", "classe": "7èmes", "section": "EB section 3"},
    {"numero": 25, "nom": "MULENDA", "post_nom": "MANDE", "classe": "7èmes", "section": "EB section 3"},
    {"numero": 26, "nom": "MULANGU", "post_nom": "wa MULANGU", "classe": "7èmes", "section": "EB section 3"}
  ],
  "8emes": [
    {"numero": 1, "nom": "MONGA", "post_nom": "RAELLE", "classe": "8èmes", "section": "EB"},
    {"numero": 2, "nom": "MONGA", "post_nom": "LIYA", "classe": "8èmes", "section": "EB"},
    {"numero": 3, "nom": "MBUI", "post_nom": "MUYUMBA", "classe": "8èmes", "section": "EB"},
    {"numero": 4, "nom": "MANDJA", "post_nom": "MUYUMBA", "classe": "8èmes", "section": "EB"},
    {"numero": 5, "nom": "MBUIYA", "post_nom": "VANGA", "classe": "8èmes", "section": "EB"},
    {"numero": 6, "nom": "MBI KARI", "post_nom": "NGO", "classe": "8èmes", "section": "EB"},
    {"numero": 7, "nom": "MAKOMBO", "post_nom": "KITENGE", "classe": "8èmes", "section": "EB"},
    {"numero": 8, "nom": "MAKOMBO", "post_nom": "MUJINGA", "classe": "8èmes", "section": "EB"},
    {"numero": 9, "nom": "LUMBU", "post_nom": "MUJINGA", "classe": "8èmes", "section": "EB"},
    {"numero": 10, "nom": "LUKWESA", "post_nom": "MARITA", "classe": "8èmes", "section": "EB"},
    {"numero": 11, "nom": "KYUNGU", "post_nom": "MUKALAY", "classe": "8èmes", "section": "EB"},
    {"numero": 12, "nom": "KONGWA", "post_nom": "MANGASA", "classe": "8èmes", "section": "EB"},
    {"numero": 13, "nom": "KI ZUMINA", "post_nom": "KIBAMBO", "classe": "8èmes", "section": "EB"},
    {"numero": 14, "nom": "KI ZANA", "post_nom": "MWE MENA", "classe": "8èmes", "section": "EB"},
    {"numero": 15, "nom": "KITENGE", "post_nom": "ROY", "classe": "8èmes", "section": "EB"},
    {"numero": 16, "nom": "KITENGE", "post_nom": "KAYA", "classe": "8èmes", "section": "EB"},
    {"numero": 17, "nom": "KIPILI KA", "post_nom": "SONGO", "classe": "8èmes", "section": "EB"},
    {"numero": 18, "nom": "KIPE NZAU", "post_nom": "ROSE", "classe": "8èmes", "section": "EB"},
    {"numero": 19, "nom": "KIBWE WA", "post_nom": "KIBWE", "classe": "8èmes", "section": "EB"},
    {"numero": 20, "nom": "KIBINGA", "post_nom": "KY EZI", "classe": "8èmes", "section": "EB"},
    {"numero": 21, "nom": "KIBALA", "post_nom": "JUNGWE", "classe": "8èmes", "section": "EB"},
    {"numero": 22, "nom": "KAZADI", "post_nom": "MBOMBO", "classe": "8èmes", "section": "EB"},
    {"numero": 23, "nom": "KA ZABI", "post_nom": "BUTACHE", "classe": "8èmes", "section": "EB"},
    {"numero": 50, "nom": "MOSEJE", "post_nom": "AKIDA", "classe": "8èmes", "section": "EB"},
    {"numero": 51, "nom": "MPOYI", "post_nom": "MUSHIJA", "classe": "8èmes", "section": "EB"},
    {"numero": 52, "nom": "MUJINGA", "post_nom": "ZINDI", "classe": "8èmes", "section": "EB"},
    {"numero": 53, "nom": "MULONGA", "post_nom": "wa KAYINDJA", "classe": "8èmes", "section": "EB"},
    {"numero": 54, "nom": "MULONGO", "post_nom": "wa KAYUMBA", "classe": "8èmes", "section": "EB"},
    {"numero": 55, "nom": "MULONGO", "post_nom": "wa SALUMU", "classe": "8èmes", "section": "EB"},
    {"numero": 56, "nom": "MULONGO", "post_nom": "Mosi", "classe": "8èmes", "section": "EB"},
    {"numero": 57, "nom": "MULEMBA", "post_nom": "Mosi", "classe": "8èmes", "section": "EB"},
    {"numero": 58, "nom": "MUSENGE", "post_nom": "wa KALUME", "classe": "8èmes", "section": "EB"},
    {"numero": 59, "nom": "MUSOWA", "post_nom": "wa MUKUMBI", "classe": "8èmes", "section": "EB"},
    {"numero": 60, "nom": "MUWAD", "post_nom": "KAWAMA", "classe": "8èmes", "section": "EB"},
    {"numero": 61, "nom": "MUWAMBA", "post_nom": "wa MULUMBWA", "classe": "8èmes", "section": "EB"},
    {"numero": 62, "nom": "MUWAMBA", "post_nom": "wa PENDA", "classe": "8èmes", "section": "EB"},
    {"numero": 63, "nom": "MUWAMBA", "post_nom": "KAWAMA", "classe": "8èmes", "section": "EB"},
    {"numero": 64, "nom": "MUWAMBA", "post_nom": "wa MULUMBWA", "classe": "8èmes", "section": "EB"},
    {"numero": 65, "nom": "MUWIKIZA", "post_nom": "BAHATI", "classe": "8èmes", "section": "EB"},
    {"numero": 66, "nom": "MUWIZA", "post_nom": "wa MUNUNGA", "classe": "8èmes", "section": "EB"},
    {"numero": 67, "nom": "NDALA", "post_nom": "MULUMBA", "classe": "8èmes", "section": "EB"},
    {"numero": 68, "nom": "NDABASI", "post_nom": "wa KALUWA", "classe": "8èmes", "section": "EB"},
    {"numero": 69, "nom": "NKRISI", "post_nom": "SAPU", "classe": "8èmes", "section": "EB"},
    {"numero": 70, "nom": "NKULU", "post_nom": "ZWADI", "classe": "8èmes", "section": "EB"},
    {"numero": 71, "nom": "NKULU", "post_nom": "ZONGO", "classe": "8èmes", "section": "EB"},
    {"numero": 72, "nom": "MWAKWA", "post_nom": "YONGO", "classe": "8èmes", "section": "EB"}
  ],
  "1ere_HP": [
    {"numero": "01", "nom": "KABWIZA", "post_nom": "NGOY", "classe": "1ère", "option": "HP"},
    {"numero": "02", "nom": "KADOMBAWA", "post_nom": "NZUNZI", "classe": "1ère", "option": "HP"},
    {"numero": "03", "nom": "KASHIMBO", "post_nom": "MITUNDA", "classe": "1ère", "option": "HP"},
    {"numero": "04", "nom": "KISIKI", "post_nom": "KAYA", "classe": "1ère", "option": "HP"},
    {"numero": "05", "nom": "KIMPUTU", "post_nom": "SAKINA", "classe": "1ère", "option": "HP"},
    {"numero": "06", "nom": "MALOBA", "post_nom": "MUTONKOLE", "classe": "1ère", "option": "HP"},
    {"numero": "07", "nom": "MBALA", "post_nom": "KASONGO", "classe": "1ère", "option": "HP"},
    {"numero": "08", "nom": "MOFYA", "post_nom": "wa MOFYA", "classe": "1ère", "option": "HP"},
    {"numero": "09", "nom": "MUTING", "post_nom": "KAYAKEZA", "classe": "1ère", "option": "HP"},
    {"numero": "10", "nom": "MUBANGA", "post_nom": "KASOMA", "classe": "1ère", "option": "HP"},
    {"numero": "11", "nom": "MUBANGA", "post_nom": "Lenge", "classe": "1ère", "option": "HP"},
    {"numero": "12", "nom": "MBIYA", "post_nom": "Lenge", "classe": "1ère", "option": "HP"},
    {"numero": "13", "nom": "MWANGE", "post_nom": "KISIMBA", "classe": "1ère", "option": "HP"},
    {"numero": "14", "nom": "MWILAMBWE", "post_nom": "KAKESE", "classe": "1ère", "option": "HP"},
    {"numero": "15", "nom": "NGODIE", "post_nom": "MWILAMBWE", "classe": "1ère", "option": "HP"},
    {"numero": "16", "nom": "KALWA", "post_nom": "KIWELE", "classe": "1ère", "option": "HP"}
  ],
  "1ere_CG": [
    {"numero": "01", "nom": "ASSINA", "post_nom": "KENDELU", "classe": "1ère", "option": "CG"},
    {"numero": "02", "nom": "AZIZA", "post_nom": "AMURI", "classe": "1ère", "option": "CG"},
    {"numero": "03", "nom": "BADIBANGA", "post_nom": "NGALULA", "classe": "1ère", "option": "CG"},
    {"numero": "04", "nom": "KABAMBA", "post_nom": "LUKOLE", "classe": "1ère", "option": "CG"},
    {"numero": "05", "nom": "KABISHI", "post_nom": "KASHIBA", "classe": "1ère", "option": "CG"},
    {"numero": "06", "nom": "KIKUSHI", "post_nom": "SUNGUBILA", "classe": "1ère", "option": "CG"},
    {"numero": "07", "nom": "KUTEMBA", "post_nom": "MULAJI", "classe": "1ère", "option": "CG"},
    {"numero": "08", "nom": "MPYANA", "post_nom": "KA BWIKA", "classe": "1ère", "option": "CG"},
    {"numero": "09", "nom": "MWAMBA", "post_nom": "MWAMBA", "classe": "1ère", "option": "CG"},
    {"numero": "10", "nom": "NJEMBA", "post_nom": "MUTOKA", "classe": "1ère", "option": "CG"},
    {"numero": "11", "nom": "PELENGE", "post_nom": "BELEP", "classe": "1ère", "option": "CG"},
    {"numero": "12", "nom": "TSHILENG", "post_nom": "TSHIBAND", "classe": "1ère", "option": "CG"},
    {"numero": "13", "nom": "SUDI", "post_nom": "SAIDI SHABANI", "classe": "1ère", "option": "CG"}
  ],
  "1ere_ELEC": [
    {"numero": "01", "nom": "BANEWE", "post_nom": "MUNYONGO", "classe": "1ère", "option": "ELEC"},
    {"numero": "02", "nom": "ILUNGA", "post_nom": "KITOKO", "classe": "1ère", "option": "ELEC"},
    {"numero": "03", "nom": "KABEYA", "post_nom": "NZENG", "classe": "1ère", "option": "ELEC"},
    {"numero": "04", "nom": "KAMANDA", "post_nom": "MWAMBI", "classe": "1ère", "option": "ELEC"},
    {"numero": "05", "nom": "KAMWASHA", "post_nom": "MAKONGA", "classe": "1ère", "option": "ELEC"},
    {"numero": "06", "nom": "KAPYA", "post_nom": "KALUMBA", "classe": "1ère", "option": "ELEC"},
    {"numero": "07", "nom": "KASONGO", "post_nom": "SELEMANI", "classe": "1ère", "option": "ELEC"},
    {"numero": "08", "nom": "MBOMBO", "post_nom": "SIKUJUA", "classe": "1ère", "option": "ELEC"},
    {"numero": "09", "nom": "MBUYU", "post_nom": "MWILAMBWE", "classe": "1ère", "option": "ELEC"},
    {"numero": "10", "nom": "MBIKAYI", "post_nom": "MEJI", "classe": "1ère", "option": "ELEC"},
    {"numero": "11", "nom": "MUKAZ", "post_nom": "KISALALA", "classe": "1ère", "option": "ELEC"},
    {"numero": "12", "nom": "MUKENDI", "post_nom": "NGOY", "classe": "1ère", "option": "ELEC"},
    {"numero": "13", "nom": "MUKUMBI", "post_nom": "MPYANA", "classe": "1ère", "option": "ELEC"},
    {"numero": "14", "nom": "MUTALA", "post_nom": "TSHIMANGA", "classe": "1ère", "option": "ELEC"},
    {"numero": "15", "nom": "MUZANGISH", "post_nom": "SAKAJI", "classe": "1ère", "option": "ELEC"},
    {"numero": "16", "nom": "NGOY", "post_nom": "KYUNGU HANSE", "classe": "1ère", "option": "ELEC"},
    {"numero": "17", "nom": "NZENZE", "post_nom": "MASAKIDI", "classe": "1ère", "option": "ELEC"},
    {"numero": "18", "nom": "NBUZI", "post_nom": "TSHAM", "classe": "1ère", "option": "ELEC"},
    {"numero": "19", "nom": "PUTA", "post_nom": "MWANSA", "classe": "1ère", "option": "ELEC"},
    {"numero": "20", "nom": "SENGA", "post_nom": "KUMBULA", "classe": "1ère", "option": "ELEC"},
    {"numero": "21", "nom": "UMBA", "post_nom": "KASONGO", "classe": "1ère", "option": "ELEC"},
    {"numero": "22", "nom": "YAV", "post_nom": "MUTEL", "classe": "1ère", "option": "ELEC"},
    {"numero": "23", "nom": "ZIMBA", "post_nom": "MUKAMBWA", "classe": "1ère", "option": "ELEC"},
    {"numero": "24", "nom": "ZONGWE", "post_nom": "KANHOLO", "classe": "1ère", "option": "ELEC"}
  ],
  "1ere_SC": [
    {"numero": "01", "nom": "AMUNASO", "post_nom": "MALISAWA", "classe": "1ère", "option": "SC"},
    {"numero": "02", "nom": "FARIDA", "post_nom": "MAKUMU", "classe": "1ère", "option": "SC"},
    {"numero": "03", "nom": "KAIND", "post_nom": "KAYAKEZA", "classe": "1ère", "option": "SC"},
    {"numero": "04", "nom": "KALOMBO", "post_nom": "NYINDU", "classe": "1ère", "option": "SC"},
    {"numero": "05", "nom": "KASONGO", "post_nom": "MWEPU", "classe": "1ère", "option": "SC"},
    {"numero": "06", "nom": "KOMBE", "post_nom": "LUFUNDA", "classe": "1ère", "option": "SC"},
    {"numero": "07", "nom": "MBUYI", "post_nom": "NDALA", "classe": "1ère", "option": "SC"},
    {"numero": "08", "nom": "MUKALAY", "post_nom": "ANNANASTASIE", "classe": "1ère", "option": "SC"},
    {"numero": "09", "nom": "MUNENENA", "post_nom": "KAHIMBA", "classe": "1ère", "option": "SC"},
    {"numero": "10", "nom": "NTAMBWE", "post_nom": "KASONGO", "classe": "1ère", "option": "SC"},
    {"numero": "11", "nom": "NTUMBA", "post_nom": "MAYOMBO", "classe": "1ère", "option": "SC"},
    {"numero": "12", "nom": "SIFA", "post_nom": "MBAMBA", "classe": "1ère", "option": "SC"},
    {"numero": "13", "nom": "SHANNEL", "post_nom": "MUJINGA", "classe": "1ère", "option": "SC"}
  ],
  "2eme_HP": [
    {"numero": "01", "nom": "BWALYA", "post_nom": "MUJINGA", "classe": "2ème", "option": "HP"},
    {"numero": "02", "nom": "MAKUMBI", "post_nom": "LUBWITA", "classe": "2ème", "option": "HP"},
    {"numero": "03", "nom": "MBBYI", "post_nom": "TANGA", "classe": "2ème", "option": "HP"},
    {"numero": "04", "nom": "MWEHU", "post_nom": "MUYUMBA", "classe": "2ème", "option": "HP"},
    {"numero": "05", "nom": "MWEPUI", "post_nom": "BANZA", "classe": "2ème", "option": "HP"},
    {"numero": "06", "nom": "MAHINGWE", "post_nom": "MWABA", "classe": "2ème", "option": "HP"},
    {"numero": "07", "nom": "NAMSANS", "post_nom": "KASHALA", "classe": "2ème", "option": "HP"},
    {"numero": "08", "nom": "LULA", "post_nom": "MARGUERITE", "classe": "2ème", "option": "HP"},
    {"numero": "09", "nom": "NGOY", "post_nom": "wa ILUNGA", "classe": "2ème", "option": "HP"},
    {"numero": "10", "nom": "NGOY", "post_nom": "MUKUTA", "classe": "2ème", "option": "HP"},
    {"numero": "11", "nom": "SAMBA", "post_nom": "MILOMBO", "classe": "2ème", "option": "HP"},
    {"numero": "12", "nom": "STARA", "post_nom": "MUSSA", "classe": "2ème", "option": "HP"},
    {"numero": "13", "nom": "TSHIBOLA", "post_nom": "TSHIBANDA", "classe": "2ème", "option": "HP"}
  ],
  "2eme_CG": [
    {"numero": "01", "nom": "ILUNGA", "post_nom": "MAKONGA", "classe": "2ème", "option": "CG"},
    {"numero": "02", "nom": "KALAMBAYI", "post_nom": "KAMANDA", "classe": "2ème", "option": "CG"},
    {"numero": "03", "nom": "KAMULETE", "post_nom": "wa SANGA", "classe": "2ème", "option": "CG"},
    {"numero": "04", "nom": "KIBALE", "post_nom": "KISIMBA", "classe": "2ème", "option": "CG"},
    {"numero": "05", "nom": "KUTWISHWA", "post_nom": "MUKENDI", "classe": "2ème", "option": "CG"},
    {"numero": "06", "nom": "MERY", "post_nom": "KATENDE", "classe": "2ème", "option": "CG"},
    {"numero": "07", "nom": "MITONGA", "post_nom": "MADOMBO", "classe": "2ème", "option": "CG"},
    {"numero": "08", "nom": "MAKOZI", "post_nom": "TSHINGOMBO", "classe": "2ème", "option": "CG"},
    {"numero": "09", "nom": "MUFUKA", "post_nom": "TSHISOLA", "classe": "2ème", "option": "CG"},
    {"numero": "10", "nom": "MUMBA", "post_nom": "EBONDO", "classe": "2ème", "option": "CG"},
    {"numero": "11", "nom": "MWAMBA", "post_nom": "TITI", "classe": "2ème", "option": "CG"},
    {"numero": "12", "nom": "NGOY", "post_nom": "KIBATI", "classe": "2ème", "option": "CG"},
    {"numero": "13", "nom": "NGOY", "post_nom": "BANZA", "classe": "2ème", "option": "CG"},
    {"numero": "14", "nom": "NTUMBA", "post_nom": "BELEPE", "classe": "2ème", "option": "CG"},
    {"numero": "15", "nom": "SHIMBI", "post_nom": "NGOY", "classe": "2ème", "option": "CG"},
    {"numero": "16", "nom": "MWEHU", "post_nom": "NYEMBO", "classe": "2ème", "option": "CG"},
    {"numero": "17", "nom": "KAZADI", "post_nom": "KANYINDA", "classe": "2ème", "option": "CG"}
  ],
  "2eme_SC": [
    {"numero": "01", "nom": "BALONDE", "post_nom": "LUKUKULA", "classe": "2ème", "option": "SC"},
    {"numero": "02", "nom": "ILUNGA", "post_nom": "BAUDOUIN", "classe": "2ème", "option": "SC"},
    {"numero": "03", "nom": "KABWIKA", "post_nom": "SAKAJI", "classe": "2ème", "option": "SC"},
    {"numero": "04", "nom": "KASHALA", "post_nom": "LUMBU", "classe": "2ème", "option": "SC"},
    {"numero": "05", "nom": "KAYOMBO", "post_nom": "MUTEBA", "classe": "2ème", "option": "SC"},
    {"numero": "06", "nom": "KILEMBO", "post_nom": "NGOY", "classe": "2ème", "option": "SC"},
    {"numero": "07", "nom": "KISIMBA", "post_nom": "KIKONDE", "classe": "2ème", "option": "SC"},
    {"numero": "08", "nom": "KYEMBE", "post_nom": "KALENGA", "classe": "2ème", "option": "SC"},
    {"numero": "09", "nom": "MAKILA", "post_nom": "LUZINGA", "classe": "2ème", "option": "SC"},
    {"numero": "10", "nom": "MALANGO", "post_nom": "KADIYA", "classe": "2ème", "option": "SC"},
    {"numero": "11", "nom": "MATEMB", "post_nom": "MU...", "classe": "2ème", "option": "SC"},
    {"numero": "12", "nom": "MUJINGA", "post_nom": "KANKONDE", "classe": "2ème", "option": "SC"},
    {"numero": "13", "nom": "NDALA", "post_nom": "KUMANDA", "classe": "2ème", "option": "SC"},
    {"numero": "14", "nom": "NDELELE", "post_nom": "KUPA KUPANGA", "classe": "2ème", "option": "SC"},
    {"numero": "15", "nom": "NGALULA", "post_nom": "KAZUMBA", "classe": "2ème", "option": "SC"},
    {"numero": "16", "nom": "NGANDWE", "post_nom": "KABASO", "classe": "2ème", "option": "SC"},
    {"numero": "17", "nom": "SHIMBA", "post_nom": "BINTI KALWA", "classe": "2ème", "option": "SC"},
    {"numero": "18", "nom": "UMBA", "post_nom": "MULONGO", "classe": "2ème", "option": "SC"},
    {"numero": "19", "nom": "KAMBA", "post_nom": "KAZ...", "classe": "2ème", "option": "SC"}
  ],
  "3eme_HP": [
    {"numero": "01", "nom": "BESA", "post_nom": "LWIMBO LUMO", "classe": "3ème", "option": "HP"},
    {"numero": "02", "nom": "BILONSA", "post_nom": "MBIYA", "classe": "3ème", "option": "HP"},
    {"numero": "03", "nom": "FAILA", "post_nom": "wa MULUMBANGA", "classe": "3ème", "option": "HP"},
    {"numero": "04", "nom": "KARITABUJA", "post_nom": "TSHIMANGA", "classe": "3ème", "option": "HP"},
    {"numero": "05", "nom": "KALUNGA", "post_nom": "TENDE", "classe": "3ème", "option": "HP"},
    {"numero": "06", "nom": "KANKU", "post_nom": "KASONGO", "classe": "3ème", "option": "HP"},
    {"numero": "07", "nom": "KASONGO", "post_nom": "KAKELA", "classe": "3ème", "option": "HP"},
    {"numero": "08", "nom": "MATILO", "post_nom": "MUNGOMBA", "classe": "3ème", "option": "HP"},
    {"numero": "09", "nom": "MALEMBA", "post_nom": "MUTINGA", "classe": "3ème", "option": "HP"},
    {"numero": "10", "nom": "MALUNGA", "post_nom": "MUNGAZA", "classe": "3ème", "option": "HP"},
    {"numero": "11", "nom": "MASUDI", "post_nom": "NYOTA", "classe": "3ème", "option": "HP"},
    {"numero": "12", "nom": "MBELA", "post_nom": "LUBO", "classe": "3ème", "option": "HP"},
    {"numero": "13", "nom": "MBUYI", "post_nom": "KAPENA", "classe": "3ème", "option": "HP"},
    {"numero": "14", "nom": "MITONGA", "post_nom": "TSHIMANGA", "classe": "3ème", "option": "HP"},
    {"numero": "15", "nom": "MWAMBA", "post_nom": "KONGOLO", "classe": "3ème", "option": "HP"},
    {"numero": "16", "nom": "MWAMBA", "post_nom": "wa MWAMBA", "classe": "3ème", "option": "HP"},
    {"numero": "17", "nom": "MWIKIZA", "post_nom": "MWAGAU", "classe": "3ème", "option": "HP"},
    {"numero": "18", "nom": "MUJINGA", "post_nom": "NGOMBE", "classe": "3ème", "option": "HP"},
    {"numero": "19", "nom": "NGOY", "post_nom": "wa NGOY", "classe": "3ème", "option": "HP"},
    {"numero": "20", "nom": "NKULU", "post_nom": "wa KYUNGU", "classe": "3ème", "option": "HP"},
    {"numero": "21", "nom": "NTAMBWE", "post_nom": "BETTY", "classe": "3ème", "option": "HP"},
    {"numero": "22", "nom": "NYEMBO", "post_nom": "EMILE", "classe": "3ème", "option": "HP"},
    {"numero": "23", "nom": "LUBAMBA", "post_nom": "KAZADI", "classe": "3ème", "option": "HP"},
    {"numero": "24", "nom": "MUKABILA", "post_nom": "MOFEYA", "classe": "3ème", "option": "HP"},
    {"numero": "25", "nom": "SANGWA", "post_nom": "wa SANGWA", "classe": "3ème", "option": "HP"},
    {"numero": "26", "nom": "TSHILA", "post_nom": "MUKONGA", "classe": "3ème", "option": "HP"},
    {"numero": "27", "nom": "TSHUNGU", "post_nom": "NGOIE", "classe": "3ème", "option": "HP"},
    {"numero": "28", "nom": "KYANGWE", "post_nom": "MUSULE", "classe": "3ème", "option": "HP"}
  ],
  "4eme_HP": [
    {"numero": 1, "nom": "KAZADI", "post_nom": "NGOIE", "classe": "4ème", "option": "HP"},
    {"numero": 2, "nom": "KIHANGA", "post_nom": "KONGOLO", "classe": "4ème", "option": "HP"},
    {"numero": 3, "nom": "LUZINGA", "post_nom": "MUYUMBA", "classe": "4ème", "option": "HP"},
    {"numero": 4, "nom": "NKULU", "post_nom": "KALENGA", "classe": "4ème", "option": "HP"},
    {"numero": 5, "nom": "TSHANDA", "post_nom": "MUKAIAYA", "classe": "4ème", "option": "HP"},
    {"numero": 6, "nom": "TSHANSA", "post_nom": "BELEPE", "classe": "4ème", "option": "HP"},
    {"numero": 7, "nom": "TSHINYAMA", "post_nom": "MUFUKA", "classe": "4ème", "option": "HP"},
    {"numero": 8, "nom": "TSHINYAMA", "post_nom": "MUFUKA", "classe": "4ème", "option": "HP"},
    {"numero": 9, "nom": "ILUNGA", "post_nom": "LULU", "classe": "4ème", "option": "HP"},
    {"numero": 10, "nom": "KALEBA", "post_nom": "LULU", "classe": "4ème", "option": "HP"},
    {"numero": 11, "nom": "HAMBABWANDI", "post_nom": "MUNTITETE", "classe": "4ème", "option": "HP"},
    {"numero": 12, "nom": "HAMBABWANDI", "post_nom": "MWIKAM", "classe": "4ème", "option": "HP"}
  ],
  "4eme_SC": [
    {"numero": 1, "nom": "ILUNGA", "post_nom": "wa ILUNGA", "classe": "4ème", "option": "SC"},
    {"numero": 2, "nom": "KABANGE", "post_nom": "FEZA", "classe": "4ème", "option": "SC"},
    {"numero": 3, "nom": "KAIMBA", "post_nom": "MUFUENGA", "classe": "4ème", "option": "SC"},
    {"numero": 4, "nom": "KALUME", "post_nom": "MWEPU", "classe": "4ème", "option": "SC"},
    {"numero": 5, "nom": "KASONGO", "post_nom": "LISTA", "classe": "4ème", "option": "SC"},
    {"numero": 6, "nom": "KYUNGU", "post_nom": "MWENZEZE", "classe": "4ème", "option": "SC"},
    {"numero": 7, "nom": "MBUGA", "post_nom": "KASHINDI", "classe": "4ème", "option": "SC"},
    {"numero": 8, "nom": "MUGO", "post_nom": "LUEWANGA NGA", "classe": "4ème", "option": "SC"},
    {"numero": 9, "nom": "MUTEKEMENA", "post_nom": "ROSE", "classe": "4ème", "option": "SC"},
    {"numero": 10, "nom": "MWAYUMA", "post_nom": "BIN NGOIE", "classe": "4ème", "option": "SC"},
    {"numero": 11, "nom": "NA NGA", "post_nom": "MBUYI", "classe": "4ème", "option": "SC"},
    {"numero": 12, "nom": "NGICA", "post_nom": "BINTI KALWA", "classe": "4ème", "option": "SC"},
    {"numero": 13, "nom": "FUNDI", "post_nom": "DEOGRATIAS", "classe": "4ème", "option": "SC"},
    {"numero": 14, "nom": "HERADI", "post_nom": "KABANGO", "classe": "4ème", "option": "SC"},
    {"numero": 15, "nom": "ISIDORE", "post_nom": "NTUMBA", "classe": "4ème", "option": "SC"},
    {"numero": 16, "nom": "KALUNGA", "post_nom": "BINKALWA", "classe": "4ème", "option": "SC"},
    {"numero": 17, "nom": "KIBALE", "post_nom": "KANKUKE", "classe": "4ème", "option": "SC"}
  ],
  "4eme_CG": [
    {"numero": 1, "nom": "ILUNGA", "post_nom": "MWAMBA", "classe": "4ème", "option": "CG"},
    {"numero": 2, "nom": "ILUNGA", "post_nom": "NGOIE", "classe": "4ème", "option": "CG"},
    {"numero": 3, "nom": "KABEYA", "post_nom": "KAPALANGA", "classe": "4ème", "option": "CG"},
    {"numero": 4, "nom": "KAKALU", "post_nom": "MUTEBA", "classe": "4ème", "option": "CG"},
    {"numero": 5, "nom": "KUNDA", "post_nom": "MUTENDE", "classe": "4ème", "option": "CG"},
    {"numero": 6, "nom": "MWAD", "post_nom": "KASENGE", "classe": "4ème", "option": "CG"},
    {"numero": 7, "nom": "NTUMBA", "post_nom": "wa MULUMBWA", "classe": "4ème", "option": "CG"},
    {"numero": 8, "nom": "SIKYALA", "post_nom": "KISALALA", "classe": "4ème", "option": "CG"},
    {"numero": 9, "nom": "KABASELE", "post_nom": "KITOKO", "classe": "4ème", "option": "CG"},
    {"numero": 10, "nom": "KATOMBA", "post_nom": "NTUMBA", "classe": "4ème", "option": "CG"},
    {"numero": 11, "nom": "MALOMBA", "post_nom": "NTUMBA", "classe": "4ème", "option": "CG"},
    {"numero": 12, "nom": "MORISHO", "post_nom": "BALISUNGU", "classe": "4ème", "option": "CG"},
    {"numero": 13, "nom": "MWAMBA", "post_nom": "NYEMBO", "classe": "4ème", "option": "CG"}
  ]
}